{"taxa": [{"species_name": "dinoflagellate", "taxonomic_rank": null}, {"species_name": "ciliate", "taxonomic_rank": null}, {"species_name": "protist", "taxonomic_rank": null}], "compounds": [{"compound_name": "okadaic acid"}], "methods": [], "environments": [{"environment_name": "marine environments"}], "markers": [], "applications": [], "relationships": [{"subject": "dinoflagellate", "predicate": "FOUND_IN", "object": "marine environments", "confidence": 1.0}, {"subject": "dinoflagellate", "predicate": "PRODUCES", "object": "red tide", "confidence": 1.0}, {"subject": "dinoflagellate", "predicate": "PRODUCES", "object": "harmful algal bloom", "confidence": 1.0}]}