{"taxa": [{"species_name": "B. plumosa", "taxonomic_rank": "species"}, {"species_name": "Bryopsis spp.", "taxonomic_rank": "genus"}, {"species_name": "Chaetomorpha", "taxonomic_rank": "genus"}], "compounds": [], "methods": [], "environments": [{"environment_name": "sampling site"}, {"environment_name": "seawater"}], "markers": [], "applications": [], "relationships": [{"subject": "B. plumosa", "predicate": "FOUND_IN", "object": "sampling site", "confidence": 1.0}, {"subject": "Bryopsis spp.", "predicate": "PRODUCES", "object": "protoplasts", "confidence": 1.0}, {"subject": "Bryopsis spp.", "predicate": "FOUND_IN", "object": "seawater", "confidence": 1.0}, {"subject": "Chaetomorpha", "predicate": "PRODUCES", "object": "aplanospores or swarmers", "confidence": 1.0}]}