{"taxa": [{"species_name": "Ulva australis", "taxonomic_rank": "species"}, {"species_name": "Ulva", "taxonomic_rank": "genus"}], "compounds": [], "methods": [], "environments": [{"environment_name": "sheltered shore"}, {"environment_name": "wave-exposed shore"}, {"environment_name": "Seongsan"}], "markers": [], "applications": [], "relationships": [{"subject": "Ulva australis", "predicate": "FOUND_IN", "object": "sheltered shore", "confidence": 1.0}, {"subject": "Ulva australis", "predicate": "FOUND_IN", "object": "wave-exposed shore", "confidence": 1.0}, {"subject": "Ulva australis", "predicate": "FOUND_IN", "object": "Seongsan", "confidence": 1.0}, {"subject": "Ulva australis", "predicate": "AFFECTS", "object": "residential animals", "confidence": 1.0}, {"subject": "Ulva australis", "predicate": "PRODUCES", "object": "frond holes", "confidence": 1.0}]}