{"taxa": [{"species_name": "Ulva", "taxonomic_rank": "genus"}], "compounds": [], "methods": [{"method_name": "repeated washing capillary pipette method"}, {"method_name": "mechanical washing"}], "environments": [], "markers": [], "applications": [], "relationships": [{"subject": "green and brown seaweeds", "predicate": "PRODUCES", "object": "motile gametes and zoospores", "confidence": 1.0}, {"subject": "motile gametes and zoospores", "predicate": "STUDIED_WITH", "object": "repeated washing capillary pipette method", "confidence": 1.0}, {"subject": "axenic cultures", "predicate": "STUDIED_WITH", "object": "repeated washing capillary pipette method", "confidence": 1.0}, {"subject": "red seaweeds", "predicate": "STUDIED_WITH", "object": "mechanical washing", "confidence": 1.0}, {"subject": "Provasoli", "predicate": "STUDIED_WITH", "object": "Ulva", "confidence": 1.0}]}