{"taxa": [{"species_name": "Microcystis aeruginosa", "taxonomic_rank": "species"}], "compounds": [{"compound_name": "NH4"}, {"compound_name": "nitrogen"}, {"compound_name": "phosphorus"}, {"compound_name": "nitrate"}], "methods": [], "environments": [{"environment_name": "Laguna de Bay, Philippines"}], "markers": [], "applications": [], "relationships": [{"subject": "Microcystis aeruginosa", "predicate": "FOUND_IN", "object": "Laguna de Bay, Philippines", "confidence": 1.0}, {"subject": "Microcystis aeruginosa", "predicate": "CONTAINS", "object": "NH4", "confidence": 0.5}, {"subject": "Microcystis aeruginosa", "predicate": "CONTAINS", "object": "nitrogen", "confidence": 0.5}, {"subject": "Microcystis aeruginosa", "predicate": "CONTAINS", "object": "phosphorus", "confidence": 0.5}, {"subject": "Microcystis aeruginosa", "predicate": "CONTAINS", "object": "nitrate", "confidence": 0.5}]}