{"taxa": [{"species_name": "Ulvella leptochaete", "taxonomic_rank": "species"}, {"species_name": "Blastophysa rhizopus", "taxonomic_rank": "species"}, {"species_name": "Bolbocoleon piliferum", "taxonomic_rank": "species"}, {"species_name": "Chondrus ocellatus", "taxonomic_rank": "species"}, {"species_name": "Ulvella viridis", "taxonomic_rank": "species"}, {"species_name": "Griffithsia japonica", "taxonomic_rank": "species"}], "compounds": [], "methods": [], "environments": [{"environment_name": "Korea"}], "markers": [], "applications": [], "relationships": [{"subject": "Ulvella leptochaete", "predicate": "FOUND_IN", "object": "Korea", "confidence": 1.0}, {"subject": "Blastophysa rhizopus", "predicate": "FOUND_IN", "object": "Korea", "confidence": 1.0}, {"subject": "Bolbocoleon piliferum", "predicate": "FOUND_IN", "object": "Korea", "confidence": 1.0}, {"subject": "Ulvella viridis", "predicate": "FOUND_IN", "object": "Korea", "confidence": 1.0}, {"subject": "Ulvella leptochaete", "predicate": "BELONGS_TO", "object": "Ulvella", "confidence": 1.0}, {"subject": "Ulvella viridis", "predicate": "BELONGS_TO", "object": "Ulvella", "confidence": 1.0}, {"subject": "Blastophysa rhizopus", "predicate": "BELONGS_TO", "object": "Blastophysa", "confidence": 1.0}, {"subject": "Bolbocoleon piliferum", "predicate": "BELONGS_TO", "object": "Bolbocoleon", "confidence": 1.0}, {"subject": "Chondrus ocellatus", "predicate": "BELONGS_TO", "object": "Chondrus", "confidence": 1.0}, {"subject": "Griffithsia japonica", "predicate": "BELONGS_TO", "object": "Griffithsia", "confidence": 1.0}]}