{"taxa": [{"species_name": "Psychrophilic microalgal strain KNF0032", "taxonomic_rank": null}, {"species_name": "KNF0024", "taxonomic_rank": null}, {"species_name": "Arctic microalgal strains", "taxonomic_rank": null}], "compounds": [{"compound_name": "fatty acids"}], "methods": [{"method_name": "growth rate investigation"}, {"method_name": "optimal growth media analysis"}], "environments": [{"environment_name": "Arctic"}], "markers": [], "applications": [{"application_name": "fatty acid production"}], "relationships": [{"subject": "Psychrophilic microalgal strain KNF0032", "predicate": "FOUND_IN", "object": "Arctic", "confidence": 0.5}, {"subject": "KNF0024", "predicate": "FOUND_IN", "object": "Arctic", "confidence": 0.5}, {"subject": "Arctic microalgal strains", "predicate": "PRODUCES", "object": "fatty acids", "confidence": 1.0}, {"subject": "Psychrophilic microalgal strain KNF0032", "predicate": "STUDIED_WITH", "object": "growth rate investigation", "confidence": 1.0}, {"subject": "KNF0024", "predicate": "STUDIED_WITH", "object": "optimal growth media analysis", "confidence": 1.0}]}