{"taxa": [{"species_name": "Chlorophyta", "taxonomic_rank": "phylum"}, {"species_name": "Chlorococcales", "taxonomic_rank": "order"}, {"species_name": "Chlorococcum", "taxonomic_rank": "genus"}, {"species_name": "Actinochloris", "taxonomic_rank": "genus"}, {"species_name": "Sphaerochlamydella", "taxonomic_rank": "genus"}, {"species_name": "Nautococcus", "taxonomic_rank": "genus"}, {"species_name": "Tetracystis", "taxonomic_rank": "genus"}, {"species_name": "Hormotila", "taxonomic_rank": "genus"}, {"species_name": "Trebouxia", "taxonomic_rank": "genus"}, {"species_name": "Bracteacoccus", "taxonomic_rank": "genus"}, {"species_name": "Myrmecia", "taxonomic_rank": "genus"}, {"species_name": "Friedmannia", "taxonomic_rank": "genus"}, {"species_name": "Treubaria", "taxonomic_rank": "genus"}, {"species_name": "Dictyochloropsis", "taxonomic_rank": "genus"}, {"species_name": "Elliptochloris", "taxonomic_rank": "genus"}, {"species_name": "Dactyosphaerium", "taxonomic_rank": "genus"}, {"species_name": "Fottea", "taxonomic_rank": "genus"}, {"species_name": "Desmococcus", "taxonomic_rank": "genus"}, {"species_name": "Apatococcus", "taxonomic_rank": "genus"}, {"species_name": "Chlorosarcinopsis", "taxonomic_rank": "genus"}, {"species_name": "Ecdysichlamys", "taxonomic_rank": "genus"}, {"species_name": "Oocystis", "taxonomic_rank": "genus"}, {"species_name": "Germinella", "taxonomic_rank": "genus"}, {"species_name": "Gloeocystis", "taxonomic_rank": "genus"}, {"species_name": "Chlorokybus", "taxonomic_rank": "genus"}, {"species_name": "Neocystis", "taxonomic_rank": "genus"}, {"species_name": "Gloeotilopsis", "taxonomic_rank": "genus"}, {"species_name": "Muriella", "taxonomic_rank": "genus"}, {"species_name": "Coenochloris", "taxonomic_rank": "genus"}, {"species_name": "Chlorella", "taxonomic_rank": "genus"}, {"species_name": "Coccomyxa", "taxonomic_rank": "genus"}, {"species_name": "Pseudococcomyxa", "taxonomic_rank": "genus"}, {"species_name": "Scotiellopsis", "taxonomic_rank": "genus"}, {"species_name": "Leptosira", "taxonomic_rank": "genus"}, {"species_name": "Lobosphaeropsis", "taxonomic_rank": "genus"}, {"species_name": "Parietochloris", "taxonomic_rank": "genus"}, {"species_name": "Pleurastrum", "taxonomic_rank": "genus"}, {"species_name": "Radiococcus", "taxonomic_rank": "genus"}, {"species_name": "Scenedesmus", "taxonomic_rank": "genus"}, {"species_name": "Charophyta", "taxonomic_rank": "phylum"}, {"species_name": "Klebsormidiales", "taxonomic_rank": "order"}, {"species_name": "Klebsormidium", "taxonomic_rank": "genus"}, {"species_name": "Stichococcus", "taxonomic_rank": "genus"}], "compounds": [], "methods": [], "environments": [], "markers": [], "applications": [], "relationships": []}