{"taxa": [{"species_name": "Thalassiosira partheneia", "taxonomic_rank": "species"}], "compounds": [], "methods": [], "environments": [{"environment_name": "warm waters"}, {"environment_name": "Incheon coast in Korea"}], "markers": [], "applications": [], "relationships": [{"subject": "Thalassiosira partheneia", "predicate": "FOUND_IN", "object": "warm waters", "confidence": 1.0}, {"subject": "Thalassiosira partheneia", "predicate": "FOUND_IN", "object": "Incheon coast in Korea", "confidence": 1.0}]}