{"taxa": [{"species_name": "Phaeodactylum tricorntum", "taxonomic_rank": "species"}], "compounds": [{"compound_name": "antioxidative substance"}], "methods": [], "environments": [], "markers": [], "applications": [{"application_name": "antioxidative activity"}, {"application_name": "antimicrobial activity"}], "relationships": [{"subject": "Phaeodactylum tricorntum", "predicate": "PRODUCES", "object": "antioxidative substance", "confidence": 1.0}, {"subject": "marine microalgae", "predicate": "PRODUCES", "object": "antioxidative activity", "confidence": 1.0}, {"subject": "marine microalgae", "predicate": "PRODUCES", "object": "antimicrobial activity", "confidence": 1.0}]}