{"taxa": [{"species_name": "P. ten-era", "taxonomic_rank": "species"}, {"species_name": "P. yezoensis", "taxonomic_rank": "species"}, {"species_name": "P. angusta", "taxonomic_rank": "species"}, {"species_name": "P. pseudolinearis", "taxonomic_rank": "species"}, {"species_name": "P. umbilicalis", "taxonomic_rank": "species"}, {"species_name": "P. dentata", "taxonomic_rank": "species"}], "compounds": [], "methods": [{"method_name": "artificial cross experiments"}, {"method_name": "interspecific crossing"}, {"method_name": "intraspecific crossing"}, {"method_name": "cross experiments"}, {"method_name": "characteristic tests"}, {"method_name": "physiological identification"}, {"method_name": "breeding studies"}], "environments": [], "markers": [{"marker_name": "color mutants"}, {"marker_name": "genetic markers"}], "applications": [{"application_name": "new cultivars"}], "relationships": [{"subject": "P. ten-era", "predicate": "BELONGS_TO", "object": "monoecious", "confidence": 1.0}, {"subject": "P. yezoensis", "predicate": "BELONGS_TO", "object": "monoecious", "confidence": 1.0}, {"subject": "P. angusta", "predicate": "BELONGS_TO", "object": "dioecious", "confidence": 1.0}, {"subject": "P. pseudolinearis", "predicate": "BELONGS_TO", "object": "dioecious", "confidence": 1.0}, {"subject": "P. umbilicalis", "predicate": "BELONGS_TO", "object": "dioecious", "confidence": 1.0}, {"subject": "P. tenera", "predicate": "STUDIED_WITH", "object": "P. yezoensis", "confidence": 1.0}, {"subject": "color mutants", "predicate": "IDENTIFIED_BY", "object": "genetic markers", "confidence": 1.0}, {"subject": "P. dentata", "predicate": "STUDIED_WITH", "object": "P. pseudolinearis", "confidence": 1.0}]}