{"taxa": [{"species_name": "Chlorella ellipsoidea", "taxonomic_rank": "species"}, {"species_name": "Isochrysis galbana", "taxonomic_rank": "species"}, {"species_name": "Heterosigma ahashiwo", "taxonomic_rank": "species"}, {"species_name": "bacillariophyceae", "taxonomic_rank": "class"}, {"species_name": "dinophyceae", "taxonomic_rank": "class"}, {"species_name": "chlorophyceae", "taxonomic_rank": "class"}, {"species_name": "haptophyceae", "taxonomic_rank": "class"}], "compounds": [{"compound_name": "chloramphenicol"}, {"compound_name": "dihydrostreptomycin sulphate"}, {"compound_name": "neomycin"}, {"compound_name": "penicillin G"}, {"compound_name": "streptomycin sulphate"}], "methods": [], "environments": [], "markers": [], "applications": [], "relationships": [{"subject": "Chlorella ellipsoidea", "predicate": "STUDIED_WITH", "object": "dihydrostreptomycin sulphate", "confidence": 1.0}, {"subject": "Isochrysis galbana", "predicate": "STUDIED_WITH", "object": "neomycin", "confidence": 1.0}, {"subject": "Heterosigma ahashiwo", "predicate": "STUDIED_WITH", "object": "neomycin", "confidence": 1.0}]}