{"taxa": [{"species_name": "Colaconema savianum", "taxonomic_rank": "species"}, {"species_name": "Acrochaetium thuretii", "taxonomic_rank": "species"}, {"species_name": "Congregatocarpus pacifica", "taxonomic_rank": "species"}, {"species_name": "Laingia pacifica", "taxonomic_rank": "species"}, {"species_name": "Constantinea rosa-marina", "taxonomic_rank": "species"}], "compounds": [], "methods": [], "environments": [{"environment_name": "southeast Kamchatka"}, {"environment_name": "Bering Sea"}, {"environment_name": "Kamchatka"}], "markers": [], "applications": [], "relationships": [{"subject": "Colaconema savianum", "predicate": "FOUND_IN", "object": "Bering Sea", "confidence": 1.0}, {"subject": "Congregatocarpus pacifica", "predicate": "FOUND_IN", "object": "Kamchatka", "confidence": 1.0}, {"subject": "Colaconema savianum", "predicate": "IDENTIFIED_BY", "object": "Acrochaetium thuretii", "confidence": 1.0}, {"subject": "Congregatocarpus pacifica", "predicate": "IDENTIFIED_BY", "object": "Laingia pacifica", "confidence": 1.0}]}