{"taxa": [{"species_name": "Oscillatoria kawamurae", "taxonomic_rank": "species"}, {"species_name": "Pseudanabaena catenata", "taxonomic_rank": "species"}, {"species_name": "Pectinatella magnifica", "taxonomic_rank": "species"}], "compounds": [], "methods": [{"method_name": "trait-based approach"}, {"method_name": "three diversity indices"}, {"method_name": "functional groups (FGs)"}, {"method_name": "morphologically based functional groups (MBFGs)"}], "environments": [{"environment_name": "large rivers of South Korea"}, {"environment_name": "two main rivers in South Korea"}, {"environment_name": "freshwater"}], "markers": [], "applications": [], "relationships": [{"subject": "Oscillatoria kawamurae", "predicate": "FOUND_IN", "object": "large rivers of South Korea", "confidence": 0.5}, {"subject": "Pseudanabaena catenata", "predicate": "FOUND_IN", "object": "large rivers of South Korea", "confidence": 0.5}, {"subject": "Oscillatoria kawamurae", "predicate": "FOUND_IN", "object": "two main rivers in South Korea", "confidence": 0.5}, {"subject": "Pseudanabaena catenata", "predicate": "FOUND_IN", "object": "two main rivers in South Korea", "confidence": 0.5}, {"subject": "Oscillatoria kawamurae", "predicate": "FOUND_IN", "object": "freshwater", "confidence": 0.5}, {"subject": "Pseudanabaena catenata", "predicate": "FOUND_IN", "object": "freshwater", "confidence": 0.5}, {"subject": "Pectinatella magnifica", "predicate": "FOUND_IN", "object": "freshwater", "confidence": 1.0}, {"subject": "Oscillatoria kawamurae", "predicate": "BELONGS_TO", "object": "Pectinatella magnifica colonies", "confidence": 1.0}, {"subject": "Pseudanabaena catenata", "predicate": "BELONGS_TO", "object": "Pectinatella magnifica colonies", "confidence": 1.0}, {"subject": "Oscillatoria kawamurae", "predicate": "STUDIED_WITH", "object": "three diversity indices", "confidence": 0.5}, {"subject": "Pseudanabaena catenata", "predicate": "STUDIED_WITH", "object": "three diversity indices", "confidence": 0.5}, {"subject": "Oscillatoria kawamurae", "predicate": "STUDIED_WITH", "object": "functional groups (FGs)", "confidence": 0.5}, {"subject": "Pseudanabaena catenata", "predicate": "STUDIED_WITH", "object": "functional groups (FGs)", "confidence": 0.5}, {"subject": "Oscillatoria kawamurae", "predicate": "STUDIED_WITH", "object": "morphologically based functional groups (MBFGs)", "confidence": 0.5}, {"subject": "Pseudanabaena catenata", "predicate": "STUDIED_WITH", "object": "morphologically based functional groups (MBFGs)", "confidence": 0.5}]}