{"taxa": [{"species_name": "L. kaiseri", "taxonomic_rank": "species"}, {"species_name": "L. congestum", "taxonomic_rank": "species"}], "compounds": [], "methods": [], "environments": [], "markers": [], "applications": [], "relationships": [{"subject": "L. kaiseri", "predicate": "BELONGS_TO", "object": "L. congestum", "confidence": 1.0}, {"subject": "L. congestum", "predicate": "IDENTIFIED_BY", "object": "Hernandez-Kantun et al. 2016", "confidence": 1.0}, {"subject": "L. congestum", "predicate": "IDENTIFIED_BY", "object": "Figueiredo and Steneck 2000", "confidence": 1.0}]}