{"taxa": [{"species_name": "Rhodophyta", "taxonomic_rank": "phylum"}, {"species_name": "Cryptonemiales", "taxonomic_rank": "order"}, {"species_name": "Gelidiaceae", "taxonomic_rank": "family"}, {"species_name": "Fucales", "taxonomic_rank": "order"}, {"species_name": "Phaeophyta", "taxonomic_rank": "phylum"}, {"species_name": "Polysiphonia", "taxonomic_rank": "genus"}, {"species_name": "Chlorophyceae", "taxonomic_rank": "class"}, {"species_name": "Phaeophyceae", "taxonomic_rank": "class"}], "compounds": [], "methods": [], "environments": [{"environment_name": "Korea"}, {"environment_name": "Reillagigedo Islands"}, {"environment_name": "Japan"}, {"environment_name": "Gojeong-Ri, west coast of Korea"}], "markers": [], "applications": [], "relationships": [{"subject": "Rhodophyta", "predicate": "BELONGS_TO", "object": "Cryptonemiales", "confidence": 1.0}, {"subject": "Cryptonemiales", "predicate": "FOUND_IN", "object": "Korea", "confidence": 1.0}, {"subject": "Gelidiaceae", "predicate": "FOUND_IN", "object": "Korea", "confidence": 1.0}, {"subject": "Fucales", "predicate": "FOUND_IN", "object": "Korea", "confidence": 1.0}, {"subject": "Fucales", "predicate": "BELONGS_TO", "object": "Phaeophyta", "confidence": 1.0}, {"subject": "Polysiphonia", "predicate": "FOUND_IN", "object": "Korea", "confidence": 1.0}, {"subject": "Chlorophyceae", "predicate": "FOUND_IN", "object": "Japan", "confidence": 1.0}, {"subject": "Phaeophyceae", "predicate": "FOUND_IN", "object": "Japan", "confidence": 1.0}]}