{"taxa": [{"species_name": "M. rubrum MR-MAL01", "taxonomic_rank": null}, {"species_name": "Teleaulax amphioxeia CR-MAL01", "taxonomic_rank": null}], "compounds": [{"compound_name": "4\u2032,5-(4,6-dichlorotriazin-2-yl) aminofluorescein (DTAF)"}], "methods": [{"method_name": "filtered onto 1.2-\u00b5m pore size filter paper"}, {"method_name": "incubated on plate medium"}, {"method_name": "epifluorescence microscope"}, {"method_name": "prepared FLB"}, {"method_name": "measured the length and width"}, {"method_name": "starved for 7 days"}, {"method_name": "subsampled using a siphon"}, {"method_name": "diluted to the target concentrations"}, {"method_name": "adding autoclaved seawater"}], "environments": [{"environment_name": "non-axenic culture"}, {"environment_name": "nutrient agar broth"}, {"environment_name": "autoclaved seawater"}], "markers": [], "applications": [], "relationships": [{"subject": "M. rubrum MR-MAL01", "predicate": "FOUND_IN", "object": "non-axenic culture", "confidence": 1.0}, {"subject": "heterotrophic bacterial cells", "predicate": "FOUND_IN", "object": "non-axenic culture", "confidence": 1.0}, {"subject": "heterotrophic bacterial cells", "predicate": "STUDIED_WITH", "object": "filtered onto 1.2-\u00b5m pore size filter paper", "confidence": 1.0}, {"subject": "heterotrophic bacterial cells", "predicate": "STUDIED_WITH", "object": "incubated on plate medium", "confidence": 1.0}, {"subject": "heterotrophic bacterial cells", "predicate": "STUDIED_WITH", "object": "epifluorescence microscope", "confidence": 1.0}, {"subject": "heterotrophic bacterial cells", "predicate": "STUDIED_WITH", "object": "prepared FLB", "confidence": 1.0}, {"subject": "FLB", "predicate": "CONTAINS", "object": "4\u2032,5-(4,6-dichlorotriazin-2-yl) aminofluorescein (DTAF)", "confidence": 1.0}, {"subject": "FLB cells", "predicate": "STUDIED_WITH", "object": "epifluorescence microscope", "confidence": 1.0}, {"subject": "FLB cells", "predicate": "STUDIED_WITH", "object": "measured the length and width", "confidence": 1.0}, {"subject": "M. rubrum MR-MAL01", "predicate": "STUDIED_WITH", "object": "starved for 7 days", "confidence": 1.0}, {"subject": "M. rubrum MR-MAL01", "predicate": "STUDIED_WITH", "object": "subsampled using a siphon", "confidence": 1.0}, {"subject": "M. rubrum MR-MAL01", "predicate": "STUDIED_WITH", "object": "diluted to the target concentrations", "confidence": 1.0}, {"subject": "M. rubrum MR-MAL01", "predicate": "STUDIED_WITH", "object": "adding autoclaved seawater", "confidence": 1.0}, {"subject": "M. rubrum MR-MAL01", "predicate": "AFFECTS", "object": "Teleaulax amphioxeia CR-MAL01", "confidence": 0.5}]}