{"taxa": [{"species_name": "C. arcii", "taxonomic_rank": "species"}, {"species_name": "C. micracanthum", "taxonomic_rank": "species"}], "compounds": [], "methods": [], "environments": [{"environment_name": "Bermuda"}, {"environment_name": "Virgin Islands"}, {"environment_name": "St. John, Virgin Is."}], "markers": [{"marker_name": "COI-5P"}, {"marker_name": "rbcL"}], "applications": [], "relationships": [{"subject": "C. arcii", "predicate": "FOUND_IN", "object": "Bermuda", "confidence": 1.0}, {"subject": "C. arcii", "predicate": "FOUND_IN", "object": "Virgin Islands", "confidence": 1.0}, {"subject": "C. arcii", "predicate": "IDENTIFIED_BY", "object": "COI-5P", "confidence": 1.0}, {"subject": "C. arcii", "predicate": "IDENTIFIED_BY", "object": "rbcL", "confidence": 1.0}, {"subject": "C. micracanthum", "predicate": "IDENTIFIED_BY", "object": "COI-5P", "confidence": 1.0}, {"subject": "C. micracanthum", "predicate": "IDENTIFIED_BY", "object": "rbcL", "confidence": 1.0}]}