{"taxa": [{"species_name": "Dinophysis rotundata", "taxonomic_rank": "species"}, {"species_name": "Ceratium fusus", "taxonomic_rank": "species"}, {"species_name": "Ceratium lineatum", "taxonomic_rank": "species"}, {"species_name": "Protoperidinium brochii", "taxonomic_rank": "species"}, {"species_name": "Protoperidinium depressum", "taxonomic_rank": "species"}, {"species_name": "Protoperidinium oceanicum", "taxonomic_rank": "species"}, {"species_name": "Chlamydomonas coccoides", "taxonomic_rank": "species"}, {"species_name": "Chlamydomonas pulsatilla", "taxonomic_rank": "species"}, {"species_name": "Euglena sp.", "taxonomic_rank": "species"}, {"species_name": "Eutreptiella gymnastica", "taxonomic_rank": "species"}, {"species_name": "Eutreptiella marina", "taxonomic_rank": "species"}, {"species_name": "Gonyaulacales", "taxonomic_rank": "order"}, {"species_name": "Ceratiaceae", "taxonomic_rank": "family"}, {"species_name": "Ceratium", "taxonomic_rank": "genus"}, {"species_name": "Peridiales", "taxonomic_rank": "order"}, {"species_name": "Protoperidiniaceae", "taxonomic_rank": "family"}, {"species_name": "Protoperidinium", "taxonomic_rank": "genus"}, {"species_name": "CHLOROPHYTA", "taxonomic_rank": "division"}, {"species_name": "Chlorophyceae", "taxonomic_rank": "class"}, {"species_name": "Volvocales", "taxonomic_rank": "order"}, {"species_name": "Chlamydomonadaceae", "taxonomic_rank": "family"}, {"species_name": "Chlamydomonas", "taxonomic_rank": "genus"}, {"species_name": "EUGLENOPHYTA", "taxonomic_rank": "division"}, {"species_name": "Euglenophyceae", "taxonomic_rank": "class"}, {"species_name": "Euglenales", "taxonomic_rank": "order"}, {"species_name": "Euglenaceae", "taxonomic_rank": "family"}, {"species_name": "Euglena", "taxonomic_rank": "genus"}, {"species_name": "Eutreptiaceae", "taxonomic_rank": "family"}, {"species_name": "Eutreptiella", "taxonomic_rank": "genus"}, {"species_name": "CHROMOPHYTA", "taxonomic_rank": "division"}, {"species_name": "Chryptophyceae", "taxonomic_rank": "class"}], "compounds": [], "methods": [], "environments": [], "markers": [], "applications": [], "relationships": [{"subject": "Dinophysis rotundata", "predicate": "BELONGS_TO", "object": "Gonyaulacales", "confidence": 1.0}, {"subject": "Ceratium fusus", "predicate": "BELONGS_TO", "object": "Ceratium", "confidence": 1.0}, {"subject": "Ceratium lineatum", "predicate": "BELONGS_TO", "object": "Ceratium", "confidence": 1.0}, {"subject": "Ceratium", "predicate": "BELONGS_TO", "object": "Ceratiaceae", "confidence": 1.0}, {"subject": "Ceratiaceae", "predicate": "BELONGS_TO", "object": "Gonyaulacales", "confidence": 1.0}, {"subject": "Protoperidinium brochii", "predicate": "BELONGS_TO", "object": "Protoperidinium", "confidence": 1.0}, {"subject": "Protoperidinium depressum", "predicate": "BELONGS_TO", "object": "Protoperidinium", "confidence": 1.0}, {"subject": "Protoperidinium oceanicum", "predicate": "BELONGS_TO", "object": "Protoperidinium", "confidence": 1.0}, {"subject": "Protoperidinium", "predicate": "BELONGS_TO", "object": "Protoperidiniaceae", "confidence": 1.0}, {"subject": "Protoperidiniaceae", "predicate": "BELONGS_TO", "object": "Peridiales", "confidence": 1.0}, {"subject": "Chlamydomonas coccoides", "predicate": "BELONGS_TO", "object": "Chlamydomonas", "confidence": 1.0}, {"subject": "Chlamydomonas pulsatilla", "predicate": "BELONGS_TO", "object": "Chlamydomonas", "confidence": 1.0}, {"subject": "Chlamydomonas", "predicate": "BELONGS_TO", "object": "Chlamydomonadaceae", "confidence": 1.0}, {"subject": "Chlamydomonadaceae", "predicate": "BELONGS_TO", "object": "Volvocales", "confidence": 1.0}, {"subject": "Volvocales", "predicate": "BELONGS_TO", "object": "Chlorophyceae", "confidence": 1.0}, {"subject": "Chlorophyceae", "predicate": "BELONGS_TO", "object": "CHLOROPHYTA", "confidence": 1.0}, {"subject": "Euglena sp.", "predicate": "BELONGS_TO", "object": "Euglena", "confidence": 1.0}, {"subject": "Euglena", "predicate": "BELONGS_TO", "object": "Euglenaceae", "confidence": 1.0}, {"subject": "Euglenaceae", "predicate": "BELONGS_TO", "object": "Euglenales", "confidence": 1.0}, {"subject": "Eutreptiella gymnastica", "predicate": "BELONGS_TO", "object": "Eutreptiella", "confidence": 1.0}, {"subject": "Eutreptiella marina", "predicate": "BELONGS_TO", "object": "Eutreptiella", "confidence": 1.0}, {"subject": "Eutreptiella", "predicate": "BELONGS_TO", "object": "Eutreptiaceae", "confidence": 1.0}, {"subject": "Eutreptiaceae", "predicate": "BELONGS_TO", "object": "Euglenales", "confidence": 1.0}, {"subject": "Euglenales", "predicate": "BELONGS_TO", "object": "Euglenophyceae", "confidence": 1.0}, {"subject": "Euglenophyceae", "predicate": "BELONGS_TO", "object": "EUGLENOPHYTA", "confidence": 1.0}, {"subject": "Chryptophyceae", "predicate": "BELONGS_TO", "object": "CHROMOPHYTA", "confidence": 1.0}]}