{"taxa": [{"species_name": "Enteromorpha micrococca", "taxonomic_rank": "species"}, {"species_name": "Blidingia minima", "taxonomic_rank": "species"}, {"species_name": "Enteromorpha nana", "taxonomic_rank": "species"}], "compounds": [], "methods": [], "environments": [{"environment_name": "southeast Kamchatka"}, {"environment_name": "Bering Sea"}, {"environment_name": "Kamchatka"}], "markers": [], "applications": [], "relationships": [{"subject": "Enteromorpha micrococca", "predicate": "FOUND_IN", "object": "southeast Kamchatka", "confidence": 1.0}, {"subject": "Enteromorpha micrococca", "predicate": "FOUND_IN", "object": "Bering Sea", "confidence": 1.0}, {"subject": "Blidingia minima", "predicate": "FOUND_IN", "object": "Kamchatka", "confidence": 1.0}, {"subject": "Blidingia minima", "predicate": "FOUND_IN", "object": "Bering Sea", "confidence": 1.0}]}