{"taxa": [{"species_name": "Dictyopteris prolifera", "taxonomic_rank": "species"}, {"species_name": "Dictyopteris latiuscula", "taxonomic_rank": "species"}, {"species_name": "Spatoglossum crassum", "taxonomic_rank": "species"}], "compounds": [], "methods": [], "environments": [{"environment_name": "Seongsan"}, {"environment_name": "Hachuja"}, {"environment_name": "Haegeumgang"}, {"environment_name": "Sangjokam"}, {"environment_name": "Anin"}, {"environment_name": "Dolsando"}], "markers": [], "applications": [], "relationships": [{"subject": "Dictyopteris prolifera", "predicate": "FOUND_IN", "object": "Seongsan", "confidence": 1.0}, {"subject": "Dictyopteris prolifera", "predicate": "FOUND_IN", "object": "Hachuja", "confidence": 1.0}, {"subject": "Dictyopteris latiuscula", "predicate": "FOUND_IN", "object": "Haegeumgang", "confidence": 1.0}, {"subject": "Dictyopteris latiuscula", "predicate": "FOUND_IN", "object": "Sangjokam", "confidence": 1.0}, {"subject": "Spatoglossum crassum", "predicate": "FOUND_IN", "object": "Anin", "confidence": 1.0}, {"subject": "Spatoglossum crassum", "predicate": "FOUND_IN", "object": "Dolsando", "confidence": 1.0}]}