{"taxa": [{"species_name": "M. chthonoplastes", "taxonomic_rank": "species"}, {"species_name": "Oscillatoria spp.", "taxonomic_rank": "genus"}, {"species_name": "Chromatium", "taxonomic_rank": "genus"}, {"species_name": "heterocystous cyanobacteria", "taxonomic_rank": null}, {"species_name": "sulfur bacteria", "taxonomic_rank": null}, {"species_name": "sulfate reducing bacteria", "taxonomic_rank": null}], "compounds": [], "methods": [], "environments": [{"environment_name": "Mellum Island"}, {"environment_name": "North Sea"}, {"environment_name": "Banana Wharf"}, {"environment_name": "Witches Brew"}, {"environment_name": "British Virgin Islands"}, {"environment_name": "intertidal flats"}], "markers": [], "applications": [], "relationships": [{"subject": "Mellum Island mats", "predicate": "FOUND_IN", "object": "intertidal flats", "confidence": 1.0}, {"subject": "Mellum Island mats", "predicate": "CONTAINS", "object": "green cyanobacterial layer", "confidence": 1.0}, {"subject": "Mellum Island mats", "predicate": "CONTAINS", "object": "red layer of sulfur bacteria", "confidence": 1.0}, {"subject": "Mellum Island mats", "predicate": "CONTAINS", "object": "black zone of sulfate reducing bacteria", "confidence": 1.0}, {"subject": "mats from Banana Wharf", "predicate": "CONTAINS", "object": "green and red layers", "confidence": 1.0}, {"subject": "mats from Banana Wharf", "predicate": "CONTAINS", "object": "orange-pink top layer", "confidence": 1.0}, {"subject": "mats from Banana Wharf", "predicate": "CONTAINS", "object": "black bottom layer", "confidence": 1.0}, {"subject": "mats we studied", "predicate": "CONTAINS", "object": "heterocystous cyanobacteria", "confidence": 0.0}, {"subject": "mats from Banana Wharf", "predicate": "CONTAINS", "object": "M. chthonoplastes", "confidence": 1.0}, {"subject": "mats from Banana Wharf", "predicate": "CONTAINS", "object": "Oscillatoria spp.", "confidence": 1.0}, {"subject": "mats from Banana Wharf", "predicate": "CONTAINS", "object": "Chromatium", "confidence": 1.0}, {"subject": "mats from Mellum Island", "predicate": "CONTAINS", "object": "M. chthonoplastes", "confidence": 1.0}, {"subject": "mats from Mellum Island", "predicate": "CONTAINS", "object": "Oscillatoria spp.", "confidence": 1.0}, {"subject": "mats from Mellum Island", "predicate": "CONTAINS", "object": "Chromatium", "confidence": 1.0}, {"subject": "mats from Witches Brew", "predicate": "CONTAINS", "object": "M. chthonoplastes", "confidence": 1.0}]}