{"taxa": [{"species_name": "C. polykrikoides", "taxonomic_rank": null}, {"species_name": "H. akashiwo", "taxonomic_rank": null}], "compounds": [{"compound_name": "free fatty acids"}, {"compound_name": "unsaturated fatty acids"}, {"compound_name": "EPA"}, {"compound_name": "eicosapentaenoic acid"}, {"compound_name": "DHA"}, {"compound_name": "docosahexaenoic acid"}, {"compound_name": "hemolysins"}, {"compound_name": "highly unsaturated fatty acids"}, {"compound_name": "saponin"}], "methods": [], "environments": [], "markers": [], "applications": [], "relationships": [{"subject": "C. polykrikoides", "predicate": "PRODUCES", "object": "unsaturated fatty acids", "confidence": 1.0}, {"subject": "C. polykrikoides", "predicate": "PRODUCES", "object": "EPA", "confidence": 1.0}, {"subject": "C. polykrikoides", "predicate": "PRODUCES", "object": "DHA", "confidence": 1.0}, {"subject": "C. polykrikoides", "predicate": "CONTAINS", "object": "hemolysins", "confidence": 1.0}, {"subject": "C. polykrikoides", "predicate": "CONTAINS", "object": "highly unsaturated fatty acids", "confidence": 1.0}, {"subject": "H. akashiwo", "predicate": "PRODUCES", "object": "hemolytic activity", "confidence": 1.0}]}