{"taxa": [], "compounds": [], "methods": [], "environments": [{"environment_name": "Kamchatka"}, {"environment_name": "Commander Islands"}, {"environment_name": "western coast of the Bering Sea"}], "markers": [], "applications": [], "relationships": [{"subject": "marine benthic algae", "predicate": "FOUND_IN", "object": "Kamchatka", "confidence": 1.0}, {"subject": "marine benthic algae", "predicate": "FOUND_IN", "object": "Commander Islands", "confidence": 1.0}, {"subject": "marine benthic algae", "predicate": "FOUND_IN", "object": "western coast of the Bering Sea", "confidence": 1.0}]}