{"taxa": [{"species_name": "Cochlodinium polykrikoides", "taxonomic_rank": "species"}, {"species_name": "phototrophic dinoflagellates", "taxonomic_rank": null}], "compounds": [], "methods": [{"method_name": "abundance measurement"}, {"method_name": "grazing impact estimation"}], "environments": [{"environment_name": "South Sea of Korea"}], "markers": [], "applications": [], "relationships": [{"subject": "Cochlodinium polykrikoides", "predicate": "FOUND_IN", "object": "South Sea of Korea", "confidence": 1.0}, {"subject": "Cochlodinium polykrikoides", "predicate": "AFFECTS", "object": "aquaculture industry", "confidence": 1.0}, {"subject": "metazooplankton", "predicate": "AFFECTS", "object": "Cochlodinium polykrikoides", "confidence": 1.0}, {"subject": "metazooplankton", "predicate": "AFFECTS", "object": "phototrophic dinoflagellates", "confidence": 1.0}]}