{"taxa": [{"species_name": "Navicula cancellata", "taxonomic_rank": "species"}, {"species_name": "Navicula retusa var. cancellata", "taxonomic_rank": "variety"}, {"species_name": "Navicula corymbosa", "taxonomic_rank": "species"}], "compounds": [], "methods": [], "environments": [{"environment_name": "Oido/Incheon (37\u00b020\u203248\u2033 N, 126\u00b040\u203257\u2033 E)"}, {"environment_name": "salt farm"}, {"environment_name": "surface water"}, {"environment_name": "Busan Pier/Busan (35\u00b006\u203217\u2033 N, 129\u00b002\u203236\u2033 E)"}, {"environment_name": "estuary"}, {"environment_name": "Tongyeong/Gyeongnam (34\u00b050\u203218\u2033 N, 128\u00b025\u203204\u2033 E)"}, {"environment_name": "coast"}], "markers": [], "applications": [], "relationships": [{"subject": "Navicula cancellata", "predicate": "FOUND_IN", "object": "Oido/Incheon (37\u00b020\u203248\u2033 N, 126\u00b040\u203257\u2033 E)", "confidence": 1.0}, {"subject": "Navicula cancellata", "predicate": "FOUND_IN", "object": "salt farm", "confidence": 1.0}, {"subject": "Navicula cancellata", "predicate": "FOUND_IN", "object": "surface water", "confidence": 1.0}, {"subject": "Navicula cancellata", "predicate": "FOUND_IN", "object": "Busan Pier/Busan (35\u00b006\u203217\u2033 N, 129\u00b002\u203236\u2033 E)", "confidence": 1.0}, {"subject": "Navicula cancellata", "predicate": "FOUND_IN", "object": "estuary", "confidence": 1.0}, {"subject": "Navicula corymbosa", "predicate": "FOUND_IN", "object": "Tongyeong/Gyeongnam (34\u00b050\u203218\u2033 N, 128\u00b025\u203204\u2033 E)", "confidence": 1.0}, {"subject": "Navicula corymbosa", "predicate": "FOUND_IN", "object": "coast", "confidence": 1.0}]}