{"taxa": [{"species_name": "G. vermiculophylla", "taxonomic_rank": "species"}, {"species_name": "G. tikvahiae", "taxonomic_rank": "species"}], "compounds": [{"compound_name": "prostaglandin E2"}], "methods": [], "environments": [{"environment_name": "LIS"}], "markers": [], "applications": [{"application_name": "Integrated Multi-Trophic Aquaculture"}], "relationships": [{"subject": "G. vermiculophylla", "predicate": "PRODUCES", "object": "prostaglandin E2", "confidence": 0.5}, {"subject": "G. vermiculophylla", "predicate": "FOUND_IN", "object": "LIS", "confidence": 1.0}, {"subject": "G. tikvahiae", "predicate": "FOUND_IN", "object": "LIS", "confidence": 1.0}, {"subject": "G. vermiculophylla", "predicate": "AFFECTS", "object": "G. tikvahiae", "confidence": 1.0}]}