{"taxa": [], "compounds": [], "methods": [{"method_name": "upright epifluorescence microscope"}, {"method_name": "hemocytometer"}], "environments": [], "markers": [], "applications": [], "relationships": [{"subject": "upright epifluorescence microscope", "predicate": "STUDIED_WITH", "object": "PE-rich taxa", "confidence": 0.5}, {"subject": "upright epifluorescence microscope", "predicate": "STUDIED_WITH", "object": "PC-rich taxa", "confidence": 0.5}, {"subject": "hemocytometer", "predicate": "STUDIED_WITH", "object": "cell abundance", "confidence": 0.5}]}