{"taxa": [{"species_name": "Pophyra", "taxonomic_rank": "genus"}], "compounds": [], "methods": [{"method_name": "culture and sensitivity tests"}], "environments": [{"environment_name": "modern aquaculture"}], "markers": [], "applications": [], "relationships": [{"subject": "Pophyra", "predicate": "AFFECTS", "object": "ammonium uptake", "confidence": 1.0}, {"subject": "antibiotic misuse", "predicate": "AFFECTS", "object": "photosynthetic apparatus", "confidence": 1.0}, {"subject": "culture and sensitivity tests", "predicate": "IDENTIFIED_BY", "object": "bacteria", "confidence": 1.0}]}