{"taxa": [{"species_name": "C. fragile subsp. fragile", "taxonomic_rank": "subspecies"}], "compounds": [], "methods": [], "environments": [{"environment_name": "Southern hemispheres"}, {"environment_name": "temperate areas throughout the globe"}, {"environment_name": "native range in Japan"}, {"environment_name": "Europe"}, {"environment_name": "Mediterranean Sea"}], "markers": [], "applications": [], "relationships": [{"subject": "C. fragile subsp. fragile", "predicate": "FOUND_IN", "object": "Southern hemispheres", "confidence": 1.0}, {"subject": "C. fragile subsp. fragile", "predicate": "FOUND_IN", "object": "temperate areas throughout the globe", "confidence": 1.0}, {"subject": "C. fragile subsp. fragile", "predicate": "FOUND_IN", "object": "native range in Japan", "confidence": 1.0}, {"subject": "C. fragile subsp. fragile", "predicate": "FOUND_IN", "object": "Europe", "confidence": 1.0}, {"subject": "C. fragile subsp. fragile", "predicate": "FOUND_IN", "object": "Mediterranean Sea", "confidence": 1.0}, {"subject": "C. fragile subsp. fragile", "predicate": "AFFECTS", "object": "resident species", "confidence": 1.0}]}