{"taxa": [{"species_name": "Ecklonia spp.", "taxonomic_rank": "genus"}], "compounds": [{"compound_name": "polyphenols"}, {"compound_name": "D-alpha-tocopherol"}], "methods": [{"method_name": "whole tissue extracts"}, {"method_name": "naked mouse study"}], "environments": [], "markers": [], "applications": [{"application_name": "protective effects against UVB induced skin carcinogenesis"}], "relationships": [{"subject": "Ecklonia spp.", "predicate": "PRODUCES", "object": "polyphenols", "confidence": 0.5}, {"subject": "polyphenols", "predicate": "STUDIED_WITH", "object": "whole tissue extracts", "confidence": 1.0}, {"subject": "polyphenols", "predicate": "STUDIED_WITH", "object": "naked mouse study", "confidence": 1.0}, {"subject": "polyphenols", "predicate": "AFFECTS", "object": "protective effects against UVB induced skin carcinogenesis", "confidence": 1.0}]}