{"taxa": [{"species_name": "Dictyopteris zonarioides", "taxonomic_rank": "species"}, {"species_name": "Laurencia hybrida", "taxonomic_rank": "species"}], "compounds": [{"compound_name": "zonarol"}, {"compound_name": "isozonarol"}, {"compound_name": "hydroquinones"}, {"compound_name": "fatty acids"}], "methods": [], "environments": [{"environment_name": "California"}, {"environment_name": "marine"}], "markers": [], "applications": [{"application_name": "antiviral"}, {"application_name": "fungitoxic"}, {"application_name": "antibacterial"}, {"application_name": "antimicrobial"}], "relationships": [{"subject": "California marine algae", "predicate": "PRODUCES", "object": "antiviral substances", "confidence": 1.0}, {"subject": "Dictyopteris zonarioides", "predicate": "PRODUCES", "object": "zonarol", "confidence": 1.0}, {"subject": "Dictyopteris zonarioides", "predicate": "PRODUCES", "object": "isozonarol", "confidence": 1.0}, {"subject": "Dictyopteris zonarioides", "predicate": "PRODUCES", "object": "hydroquinones", "confidence": 1.0}, {"subject": "zonarol", "predicate": "BELONGS_TO", "object": "hydroquinones", "confidence": 0.5}, {"subject": "isozonarol", "predicate": "BELONGS_TO", "object": "hydroquinones", "confidence": 0.5}, {"subject": "hydroquinones", "predicate": "AFFECTS", "object": "fungitoxic", "confidence": 1.0}, {"subject": "Algae", "predicate": "PRODUCES", "object": "antibacterial components", "confidence": 1.0}, {"subject": "marine benthic algae", "predicate": "CONTAINS", "object": "fatty acids", "confidence": 1.0}, {"subject": "Laurencia hybrida", "predicate": "PRODUCES", "object": "antimicrobial components", "confidence": 1.0}]}