{"taxa": [{"species_name": "cyanobacterial mats", "taxonomic_rank": null}], "compounds": [], "methods": [], "environments": [{"environment_name": "Caribbean"}, {"environment_name": "Bahamas"}, {"environment_name": "British Virgin Islands"}, {"environment_name": "hypersaline ponds"}, {"environment_name": "BVI salt ponds"}], "markers": [], "applications": [], "relationships": [{"subject": "cyanobacterial mats", "predicate": "FOUND_IN", "object": "Caribbean", "confidence": 0.5}, {"subject": "cyanobacterial mats", "predicate": "FOUND_IN", "object": "Bahamas", "confidence": 0.5}, {"subject": "cyanobacterial mats", "predicate": "FOUND_IN", "object": "British Virgin Islands", "confidence": 0.5}, {"subject": "cyanobacterial mats", "predicate": "FOUND_IN", "object": "hypersaline ponds", "confidence": 1.0}, {"subject": "cyanobacterial mats", "predicate": "FOUND_IN", "object": "BVI salt ponds", "confidence": 1.0}]}