{"taxa": [{"species_name": "S. gracilenta", "taxonomic_rank": "species"}, {"species_name": "T. amphioxeia", "taxonomic_rank": "species"}, {"species_name": "Teleaulax", "taxonomic_rank": "genus"}], "compounds": [], "methods": [], "environments": [{"environment_name": "natural environments"}, {"environment_name": "natural seawater"}], "markers": [], "applications": [], "relationships": [{"subject": "S. gracilenta", "predicate": "FOUND_IN", "object": "natural environments", "confidence": 0.5}, {"subject": "S. gracilenta", "predicate": "AFFECTS", "object": "T. amphioxeia", "confidence": 0.5}, {"subject": "Teleaulax", "predicate": "FOUND_IN", "object": "natural seawater", "confidence": 1.0}]}