{"taxa": [], "compounds": [], "methods": [{"method_name": "optical oxygen sensor spot"}, {"method_name": "fiber optic connection"}, {"method_name": "Fibox 3"}, {"method_name": "oxygen consumption measurement"}, {"method_name": "incubation under dark conditions"}], "environments": [{"environment_name": "field conditions"}], "markers": [], "applications": [], "relationships": [{"subject": "optical oxygen sensor spot", "predicate": "STUDIED_WITH", "object": "fiber optic connection", "confidence": 1.0}, {"subject": "fiber optic connection", "predicate": "STUDIED_WITH", "object": "Fibox 3", "confidence": 1.0}, {"subject": "oxygen consumption measurement", "predicate": "STUDIED_WITH", "object": "incubation under dark conditions", "confidence": 1.0}, {"subject": "oxygen consumption measurement", "predicate": "FOUND_IN", "object": "field conditions", "confidence": 1.0}]}