{"taxa": [], "compounds": [{"compound_name": "Chl a"}], "methods": [{"method_name": "\uc0c1\uad00\ubd84\uc11d"}, {"method_name": "\ubd84\uc0b0\ubd84\uc11d"}, {"method_name": "\ud68c\uadc0\ubaa8\ud615"}, {"method_name": "\uc694\uc778\ubd84\uc11d"}], "environments": [{"environment_name": "\ub0a8\uac15\ub310"}, {"environment_name": "\uc548\ub3d9\ub310"}, {"environment_name": "\ud569\ucc9c\ub310"}], "markers": [], "applications": [], "relationships": [{"subject": "Chl a", "predicate": "STUDIED_WITH", "object": "\uc0c1\uad00\ubd84\uc11d", "confidence": 1.0}, {"subject": "Chl a", "predicate": "STUDIED_WITH", "object": "\ubd84\uc0b0\ubd84\uc11d", "confidence": 1.0}, {"subject": "Chl a", "predicate": "STUDIED_WITH", "object": "\ud68c\uadc0\ubaa8\ud615", "confidence": 1.0}, {"subject": "Chl a", "predicate": "STUDIED_WITH", "object": "\uc694\uc778\ubd84\uc11d", "confidence": 1.0}]}