{"taxa": [{"species_name": "Alsidium oliveiranum", "taxonomic_rank": "species"}, {"species_name": "Alsidium", "taxonomic_rank": "genus"}], "compounds": [], "methods": [{"method_name": "molecular studies"}, {"method_name": "morphological studies"}], "environments": [{"environment_name": "Brazilian"}], "markers": [], "applications": [], "relationships": [{"subject": "Alsidium oliveiranum", "predicate": "BELONGS_TO", "object": "Alsidium", "confidence": 1.0}, {"subject": "Alsidium oliveiranum", "predicate": "FOUND_IN", "object": "Brazilian", "confidence": 1.0}, {"subject": "molecular studies", "predicate": "STUDIED_WITH", "object": "Alsidium oliveiranum", "confidence": 1.0}, {"subject": "morphological studies", "predicate": "STUDIED_WITH", "object": "Alsidium oliveiranum", "confidence": 1.0}]}