{"taxa": [{"species_name": "Pyropia yezoensis", "taxonomic_rank": "species"}], "compounds": [], "methods": [{"method_name": "morphological characteristics"}, {"method_name": "cornmeal agar culture"}, {"method_name": "DNA template analysis"}, {"method_name": "metagenomic studies"}], "environments": [{"environment_name": "Biando, Gunsan, Korea"}, {"environment_name": "Korean coast"}, {"environment_name": "Aphaedo, Shinan, Korea"}, {"environment_name": "Nakdong River estuary"}, {"environment_name": "Pyropia aquaculture region"}], "markers": [], "applications": [], "relationships": [{"subject": "Pyropia yezoensis", "predicate": "FOUND_IN", "object": "Biando, Gunsan, Korea", "confidence": 1.0}, {"subject": "Pyropia yezoensis", "predicate": "FOUND_IN", "object": "Korean coast", "confidence": 1.0}, {"subject": "Pyropia yezoensis", "predicate": "FOUND_IN", "object": "Aphaedo, Shinan, Korea", "confidence": 1.0}, {"subject": "Pyropia yezoensis", "predicate": "FOUND_IN", "object": "Pyropia aquaculture region", "confidence": 1.0}, {"subject": "Pyropia yezoensis", "predicate": "STUDIED_WITH", "object": "morphological characteristics", "confidence": 1.0}, {"subject": "Pyropia yezoensis", "predicate": "STUDIED_WITH", "object": "cornmeal agar culture", "confidence": 1.0}, {"subject": "Pyropia yezoensis", "predicate": "STUDIED_WITH", "object": "DNA template analysis", "confidence": 1.0}, {"subject": "Pyropia yezoensis", "predicate": "STUDIED_WITH", "object": "metagenomic studies", "confidence": 1.0}]}