{"taxa": [{"species_name": "H. triquetra", "taxonomic_rank": null}, {"species_name": "A. sanguinea", "taxonomic_rank": null}], "compounds": [], "methods": [{"method_name": "enriched f/2 seawater media without silicate"}, {"method_name": "controlled-temperature chamber"}], "environments": [{"environment_name": "Shiwha Bay, Korea"}, {"environment_name": "Scripps Institution of Oceanography, University of California, San Diego, CA, USA"}], "markers": [], "applications": [], "relationships": [{"subject": "H. triquetra", "predicate": "FOUND_IN", "object": "Shiwha Bay, Korea", "confidence": 1.0}, {"subject": "A. sanguinea", "predicate": "FOUND_IN", "object": "Scripps Institution of Oceanography, University of California, San Diego, CA, USA", "confidence": 1.0}]}