{"taxa": [{"species_name": "Conferva simplex", "taxonomic_rank": "species"}, {"species_name": "Digenea subarticulata", "taxonomic_rank": "species"}, {"species_name": "Bryocladia", "taxonomic_rank": "genus"}, {"species_name": "Digenea arenahauriens", "taxonomic_rank": "species"}, {"species_name": "Digenea cymatophila", "taxonomic_rank": "species"}], "compounds": [], "methods": [], "environments": [{"environment_name": "KwaZulu-Natal, South Africa"}, {"environment_name": "Bermuda"}, {"environment_name": "Hawaii"}], "markers": [], "applications": [], "relationships": [{"subject": "Conferva simplex", "predicate": "BELONGS_TO", "object": "Digenea", "confidence": 0.5}, {"subject": "Digenea subarticulata", "predicate": "FOUND_IN", "object": "KwaZulu-Natal, South Africa", "confidence": 1.0}, {"subject": "Digenea subarticulata", "predicate": "BELONGS_TO", "object": "Bryocladia", "confidence": 1.0}, {"subject": "Digenea arenahauriens", "predicate": "FOUND_IN", "object": "Bermuda", "confidence": 1.0}, {"subject": "Digenea cymatophila", "predicate": "FOUND_IN", "object": "Hawaii", "confidence": 1.0}]}