{"taxa": [{"species_name": "Synechococcus", "taxonomic_rank": "genus"}], "compounds": [], "methods": [], "environments": [{"environment_name": "estuarine waters"}, {"environment_name": "coastal waters"}], "markers": [], "applications": [], "relationships": [{"subject": "Synechococcus", "predicate": "FOUND_IN", "object": "estuarine waters", "confidence": 0.5}, {"subject": "Synechococcus", "predicate": "FOUND_IN", "object": "coastal waters", "confidence": 0.5}, {"subject": "estuarine waters", "predicate": "AFFECTS", "object": "river runoff", "confidence": 1.0}, {"subject": "coastal waters", "predicate": "AFFECTS", "object": "river runoff", "confidence": 1.0}]}