{"taxa": [{"species_name": "basicrassa Kloczcova et Krupnova", "taxonomic_rank": "species"}, {"species_name": "Laminaria appressizhiza", "taxonomic_rank": "species"}, {"species_name": "Laminaria inclinatorhiza", "taxonomic_rank": "species"}, {"species_name": "Laminaria multiplicata", "taxonomic_rank": "species"}, {"species_name": "Laminaria", "taxonomic_rank": "genus"}], "compounds": [], "methods": [], "environments": [{"environment_name": "Russian Pacific"}, {"environment_name": "Sea of Okhotsk"}], "markers": [], "applications": [], "relationships": [{"subject": "Laminaria appressizhiza", "predicate": "BELONGS_TO", "object": "Laminaria", "confidence": 0.5}, {"subject": "Laminaria inclinatorhiza", "predicate": "BELONGS_TO", "object": "Laminaria", "confidence": 0.5}, {"subject": "Laminaria multiplicata", "predicate": "BELONGS_TO", "object": "Laminaria", "confidence": 0.5}, {"subject": "Laminaria multiplicata", "predicate": "FOUND_IN", "object": "Sea of Okhotsk", "confidence": 1.0}]}