{"taxa": [{"species_name": "Bangiaceae", "taxonomic_rank": "family"}, {"species_name": "Porphyra s. l.", "taxonomic_rank": "genus"}, {"species_name": "Pyropia kinositae", "taxonomic_rank": "species"}, {"species_name": "Pyropia moriensis", "taxonomic_rank": "species"}, {"species_name": "Pyropia onoi", "taxonomic_rank": "species"}, {"species_name": "Pyropia retorta sp. nov.", "taxonomic_rank": "species"}, {"species_name": "Pyropia yezonesis", "taxonomic_rank": "species"}], "compounds": [], "methods": [{"method_name": "morphology"}, {"method_name": "rbcL sequence data"}, {"method_name": "molecular data"}, {"method_name": "molecular comparison"}, {"method_name": "comparative morphological studies"}], "environments": [{"environment_name": "Korean coast"}, {"environment_name": "east coast of Korea"}, {"environment_name": "North Korea"}, {"environment_name": "east coast of South Korea"}, {"environment_name": "Hokkaido, Japan"}], "markers": [{"marker_name": "rbcL"}], "applications": [{"application_name": "Korean fisheries"}, {"application_name": "aquaculture techniques"}], "relationships": [{"subject": "Bangiaceae", "predicate": "BELONGS_TO", "object": "Porphyra s. l.", "confidence": 1.0}, {"subject": "Pyropia kinositae", "predicate": "FOUND_IN", "object": "east coast of Korea", "confidence": 1.0}, {"subject": "Pyropia moriensis", "predicate": "FOUND_IN", "object": "east coast of Korea", "confidence": 1.0}, {"subject": "Pyropia onoi", "predicate": "FOUND_IN", "object": "east coast of South Korea", "confidence": 1.0}, {"subject": "Pyropia retorta sp. nov.", "predicate": "FOUND_IN", "object": "east coast of Korea", "confidence": 1.0}, {"subject": "Pyropia kinositae", "predicate": "FOUND_IN", "object": "Hokkaido, Japan", "confidence": 1.0}, {"subject": "Pyropia moriensis", "predicate": "FOUND_IN", "object": "Hokkaido, Japan", "confidence": 1.0}, {"subject": "Pyropia onoi", "predicate": "FOUND_IN", "object": "North Korea", "confidence": 1.0}, {"subject": "Pyropia species", "predicate": "STUDIED_WITH", "object": "morphology", "confidence": 1.0}, {"subject": "Pyropia species", "predicate": "STUDIED_WITH", "object": "rbcL sequence data", "confidence": 1.0}, {"subject": "Pyropia onoi", "predicate": "IDENTIFIED_BY", "object": "molecular data", "confidence": 1.0}, {"subject": "foliose Bangiales", "predicate": "STUDIED_WITH", "object": "molecular comparison", "confidence": 1.0}, {"subject": "foliose Bangiales", "predicate": "STUDIED_WITH", "object": "comparative morphological studies", "confidence": 1.0}, {"subject": "Bangiaceae", "predicate": "AFFECTS", "object": "Korean fisheries", "confidence": 1.0}, {"subject": "Bangiaceae", "predicate": "AFFECTS", "object": "aquaculture techniques", "confidence": 1.0}]}