{"taxa": [{"species_name": "Capillus sp. 2.1", "taxonomic_rank": "species"}, {"species_name": "C. salinus sp. nov.", "taxonomic_rank": "species"}, {"species_name": "Capillus sp.", "taxonomic_rank": "species"}], "compounds": [], "methods": [], "environments": [{"environment_name": "bank of a river with highly saline water in India"}, {"environment_name": "halophilic environments"}, {"environment_name": "marine tidal pools"}, {"environment_name": "salt marsh"}], "markers": [], "applications": [], "relationships": [{"subject": "Capillus sp. 2.1", "predicate": "FOUND_IN", "object": "bank of a river with highly saline water in India", "confidence": 1.0}, {"subject": "C. salinus sp. nov.", "predicate": "FOUND_IN", "object": "marine tidal pools", "confidence": 1.0}, {"subject": "Capillus sp. 2.1", "predicate": "BELONGS_TO", "object": "halophilic environments", "confidence": 1.0}, {"subject": "C. salinus sp. nov.", "predicate": "BELONGS_TO", "object": "halophilic environments", "confidence": 1.0}, {"subject": "Capillus sp.", "predicate": "FOUND_IN", "object": "salt marsh", "confidence": 1.0}]}