{"taxa": [{"species_name": "macroalgae", "taxonomic_rank": null}, {"species_name": "sea-grass", "taxonomic_rank": null}, {"species_name": "giant kelp", "taxonomic_rank": null}], "compounds": [], "methods": [], "environments": [{"environment_name": "coastal areas"}, {"environment_name": "upwelling"}, {"environment_name": "estuary"}, {"environment_name": "near shore"}, {"environment_name": "coral reef"}, {"environment_name": "kelp forests"}, {"environment_name": "open ocean"}, {"environment_name": "seagrass beds"}, {"environment_name": "giant kelp forest"}, {"environment_name": "surrounded seawater"}, {"environment_name": "mesocosm"}], "markers": [], "applications": [], "relationships": [{"subject": "macroalgae", "predicate": "FOUND_IN", "object": "coastal areas", "confidence": 0.5}, {"subject": "sea-grass", "predicate": "FOUND_IN", "object": "coastal areas", "confidence": 0.5}, {"subject": "giant kelp", "predicate": "FOUND_IN", "object": "giant kelp forest", "confidence": 1.0}, {"subject": "giant kelp forest", "predicate": "FOUND_IN", "object": "coastal areas", "confidence": 0.5}, {"subject": "seagrass beds", "predicate": "FOUND_IN", "object": "coastal areas", "confidence": 0.5}]}