{"taxa": [], "compounds": [{"compound_name": "alginic acid"}, {"compound_name": "sulphated polysaccharides"}], "methods": [], "environments": [], "markers": [], "applications": [], "relationships": [{"subject": "alginic acid", "predicate": "CONTAINS", "object": "grains", "confidence": 1.0}, {"subject": "cytoplasm", "predicate": "CONTAINS", "object": "sulphated polysaccharides", "confidence": 1.0}, {"subject": "cytoplasmic vacuoles", "predicate": "CONTAINS", "object": "alginic acid", "confidence": 1.0}]}