{"taxa": [{"species_name": "Bolbocoleon piliferum", "taxonomic_rank": "species"}, {"species_name": "Grateloupia", "taxonomic_rank": "genus"}], "compounds": [], "methods": [], "environments": [{"environment_name": "marine water"}, {"environment_name": "brackish water"}, {"environment_name": "Korea"}, {"environment_name": "Japan"}], "markers": [], "applications": [], "relationships": [{"subject": "Bolbocoleon piliferum", "predicate": "FOUND_IN", "object": "marine water", "confidence": 1.0}, {"subject": "Bolbocoleon piliferum", "predicate": "FOUND_IN", "object": "brackish water", "confidence": 1.0}, {"subject": "Bolbocoleon piliferum", "predicate": "FOUND_IN", "object": "Korea", "confidence": 1.0}, {"subject": "Bolbocoleon piliferum", "predicate": "FOUND_IN", "object": "Japan", "confidence": 1.0}, {"subject": "endophytic green algae", "predicate": "FOUND_IN", "object": "Grateloupia", "confidence": 1.0}]}