{"taxa": [], "compounds": [], "methods": [], "environments": [{"environment_name": "Korea"}, {"environment_name": "East Sea coast of Korea"}, {"environment_name": "temperate zones"}, {"environment_name": "cultivation area"}], "markers": [], "applications": [], "relationships": [{"subject": "Korea", "predicate": "BELONGS_TO", "object": "temperate zones", "confidence": 1.0}, {"subject": "East Sea coast of Korea", "predicate": "FOUND_IN", "object": "Korea", "confidence": 1.0}, {"subject": "cultivation area", "predicate": "FOUND_IN", "object": "Korea", "confidence": 0.5}]}